[{"name":"meta_request.log","payload":{"filename":"/Users/wenshan/Desktop/ClearTerms/app/views/companies/index.html.erb","line":11,"method":"_app_views_companies_index_html_erb___3666377249319336878_70172971939320","message":"  \u001b[1m\u001b[36mCompany Load (0.2ms)\u001b[0m  \u001b[1m\u001b[34mSELECT \"companies\".* FROM \"companies\" ORDER BY name\u001b[0m","level":"debug"},"time":0,"transaction_id":0,"end":0,"children":[],"duration":0.0},{"name":"meta_request.log","payload":{"filename":"/Users/wenshan/Desktop/ClearTerms/app/views/companies/index.html.erb","line":11,"method":"_app_views_companies_index_html_erb___3666377249319336878_70172971939320","message":"  ↳ app/views/companies/index.html.erb:11","level":"debug"},"time":0,"transaction_id":0,"end":0,"children":[],"duration":0.0},{"name":"sql.active_record","payload":{"sql":"SELECT \"companies\".* FROM \"companies\" ORDER BY name","name":"Company Load","binds":[],"type_casted_binds":[],"statement_name":null,"connection_id":70172951655960,"filename":"/Users/wenshan/Desktop/ClearTerms/app/views/companies/index.html.erb","line":11,"method":"_app_views_companies_index_html_erb___3666377249319336878_70172971939320"},"time":"2021-05-16T23:53:35.769-04:00","transaction_id":"2899a07882bc9269cc35","end":"2021-05-16T23:53:35.769-04:00","children":[],"duration":0.8099999999999999},{"name":"render_template.action_view","payload":{"identifier":"/Users/wenshan/Desktop/ClearTerms/app/views/companies/index.html.erb","layout":"layouts/application"},"time":"2021-05-16T23:53:35.768-04:00","transaction_id":"2899a07882bc9269cc35","end":"2021-05-16T23:53:35.807-04:00","children":[],"duration":38.975},{"name":"meta_request.log","payload":{"filename":"/Users/wenshan/Desktop/ClearTerms/app/views/layouts/application.html.erb","line":17,"method":"_app_views_layouts_application_html_erb___2928515727416067946_70172890616860","message":null,"level":"info"},"time":0,"transaction_id":0,"end":0,"children":[],"duration":0.0},{"name":"render_partial.action_view","payload":{"identifier":"/Users/wenshan/Desktop/ClearTerms/app/views/partials/_nav.html.erb","cache_hit":null},"time":"2021-05-16T23:53:35.971-04:00","transaction_id":"2899a07882bc9269cc35","end":"2021-05-16T23:53:35.972-04:00","children":[],"duration":0.786},{"name":"meta_request.log","payload":{"filename":"/Users/wenshan/Desktop/ClearTerms/app/views/layouts/application.html.erb","line":19,"method":"_app_views_layouts_application_html_erb___2928515727416067946_70172890616860","message":null,"level":"info"},"time":0,"transaction_id":0,"end":0,"children":[],"duration":0.0},{"name":"render_partial.action_view","payload":{"identifier":"/Users/wenshan/Desktop/ClearTerms/app/views/partials/_footer.html.erb","cache_hit":null},"time":"2021-05-16T23:53:35.973-04:00","transaction_id":"2899a07882bc9269cc35","end":"2021-05-16T23:53:35.974-04:00","children":[],"duration":0.758},{"name":"process_action.action_controller","payload":{"controller":"CompaniesController","action":"index","params":{"controller":"companies","action":"index"},"headers":{"SCRIPT_NAME":"","QUERY_STRING":"","SERVER_PROTOCOL":"HTTP/1.1","SERVER_SOFTWARE":"puma 3.12.6 Llamas in Pajamas","GATEWAY_INTERFACE":"CGI/1.2","REQUEST_METHOD":"GET","REQUEST_PATH":"/companies","REQUEST_URI":"/companies","HTTP_VERSION":"HTTP/1.1","HTTP_HOST":"localhost:3000","HTTP_CONNECTION":"keep-alive","HTTP_SEC_CH_UA":"\" Not A;Brand\";v=\"99\", \"Chromium\";v=\"90\", \"Google Chrome\";v=\"90\"","HTTP_ACCEPT":"text/html, application/xhtml+xml","HTTP_TURBOLINKS_REFERRER":"http://localhost:3000/home","HTTP_SEC_CH_UA_MOBILE":"?0","HTTP_USER_AGENT":"Mozilla/5.0 (Macintosh; Intel Mac OS X 10_15_7) AppleWebKit/537.36 (KHTML, like Gecko) Chrome/90.0.4430.212 Safari/537.36","HTTP_SEC_FETCH_SITE":"same-origin","HTTP_SEC_FETCH_MODE":"cors","HTTP_SEC_FETCH_DEST":"empty","HTTP_REFERER":"http://localhost:3000/home","HTTP_ACCEPT_ENCODING":"gzip, deflate, br","HTTP_ACCEPT_LANGUAGE":"en-US,en;q=0.9","HTTP_COOKIE":"BetterErrors-has-used-console=true; BetterErrors-2.9.1-CSRF-Token=8fd2b2b0-6bc4-4544-872e-d7cd33586748; _clear_terms_session=iJynOZtPUsHFMY%2BznmDNCUsV5PkgyCjUx3Z5fonhC5z0jW1%2BwtmVBKZkdZgZQxVXrwCCAVpIr96T%2BfMlI5OC%2Bl8X8IDVt9zCrPQYE2Kqi4rA%2BtMmEkUjyMXNivfVjJq0JvGKlalCH%2FqzbGXi3w%3D%3D--OzX7q6o1Kb5hvQVS--WbK0pxTubgCo98ycVea0Uw%3D%3D","SERVER_NAME":"localhost","SERVER_PORT":"3000","PATH_INFO":"/companies","REMOTE_ADDR":"::1","ROUTES_70172910786240_SCRIPT_NAME":"","ORIGINAL_FULLPATH":"/companies","ORIGINAL_SCRIPT_NAME":""},"format":"html","method":"GET","path":"/companies","status":200,"view_runtime":207.84399996045977,"db_runtime":0.2490000333636999},"time":"2021-05-16T23:53:35.765-04:00","transaction_id":"2899a07882bc9269cc35","end":"2021-05-16T23:53:35.974-04:00","children":[],"duration":208.968}]